cassandra_s3_incremental_backup_watcher/__init__.py
cassandra_s3_incremental_backup_watcher/main.py
cassandra_s3_incremental_backup_watcher/sstable.py
cassandra_s3_incremental_backup_watcher/transfer.py
cassandra_s3_incremental_backup_watcher/util.py
cassandra_s3_incremental_backup_watcher-0.1.1.dist-info/DESCRIPTION.rst
cassandra_s3_incremental_backup_watcher-0.1.1.dist-info/METADATA
cassandra_s3_incremental_backup_watcher-0.1.1.dist-info/RECORD
cassandra_s3_incremental_backup_watcher-0.1.1.dist-info/WHEEL
cassandra_s3_incremental_backup_watcher-0.1.1.dist-info/entry_points.txt
cassandra_s3_incremental_backup_watcher-0.1.1.dist-info/metadata.json
cassandra_s3_incremental_backup_watcher-0.1.1.dist-info/top_level.txt
