Metadata-Version: 2.0
Name: cassandra-s3-incremental-backup-watcher
Version: 0.1.1
Summary: Continuously end Cassandra incremental backups to Amazon S3
Home-page: https://github.com/Cobliteam/cassandra-s3-incremental-backup-watcher
Author: Daniel Miranda
Author-email: daniel@cobli.co
License: MIT
Download-URL: https://github.com/Cobliteam/cassandra-s3-incremental-backup-watcher/archive/0.1.1.tar.gz
Keywords: cassandra backup incremental-backups aws s3
Platform: UNKNOWN
Requires-Dist: boto3
Requires-Dist: future
Requires-Dist: watchdog
